detectk/__init__.py
detectk/check.py
detectk/exceptions.py
detectk/models.py
detectk/base/__init__.py
detectk/base/alerter.py
detectk/base/collector.py
detectk/base/detector.py
detectk/base/storage.py
detectk/cli/__init__.py
detectk/cli/init_project.py
detectk/cli/main.py
detectk/cli/selector.py
detectk/config/__init__.py
detectk/config/loader.py
detectk/config/models.py
detectk/config/profiles.py
detectk/registry/__init__.py
detectk/registry/alerter.py
detectk/registry/base.py
detectk/registry/collector.py
detectk/registry/detector.py
detectk/registry/storage.py
detectk-0.4.1.dist-info/METADATA
detectk-0.4.1.dist-info/WHEEL
detectk-0.4.1.dist-info/entry_points.txt
detectk-0.4.1.dist-info/top_level.txt
detectk-0.4.1.dist-info/RECORD
